{
"meta":{"test_sets":[],"test_metrics":[],"learn_metrics":[{"best_value":"Min","name":"RMSE"}],"launch_mode":"Train","parameters":"","iteration_count":400,"learn_sets":["learn"],"name":"experiment"},
"iterations":[
{"learn":[73.15869642],"iteration":0,"passed_time":0.1425190802,"remaining_time":56.86511299},
{"learn":[70.00090462],"iteration":1,"passed_time":0.1433627854,"remaining_time":28.5291943},
{"learn":[66.68113704],"iteration":2,"passed_time":0.1438263048,"remaining_time":19.03301434},
{"learn":[64.08714102],"iteration":3,"passed_time":0.1442063167,"remaining_time":14.27642535},
{"learn":[61.78466442],"iteration":4,"passed_time":0.1445150746,"remaining_time":11.41669089},
{"learn":[59.48428708],"iteration":5,"passed_time":0.1449223727,"remaining_time":9.516569141},
{"learn":[57.24712226],"iteration":6,"passed_time":0.1452548391,"remaining_time":8.15502168},
{"learn":[55.18012769],"iteration":7,"passed_time":0.1456800812,"remaining_time":7.138323977},
{"learn":[53.30559856],"iteration":8,"passed_time":0.1459593803,"remaining_time":6.341124188},
{"learn":[51.63033304],"iteration":9,"passed_time":0.1462897182,"remaining_time":5.70529901},
{"learn":[50.04325205],"iteration":10,"passed_time":0.1465478212,"remaining_time":5.182463858},
{"learn":[48.65765096],"iteration":11,"passed_time":0.1469091164,"remaining_time":4.75006143},
{"learn":[47.4925261],"iteration":12,"passed_time":0.1472597168,"remaining_time":4.383808494},
{"learn":[46.41328399],"iteration":13,"passed_time":0.1475629125,"remaining_time":4.068520301},
{"learn":[45.08168782],"iteration":14,"passed_time":0.1477978515,"remaining_time":3.793478188},
{"learn":[43.85058707],"iteration":15,"passed_time":0.1480697768,"remaining_time":3.553674644},
{"learn":[42.97490756],"iteration":16,"passed_time":0.1483100123,"remaining_time":3.341337336},
{"learn":[41.9934652],"iteration":17,"passed_time":0.1485613311,"remaining_time":3.152801581},
{"learn":[41.0436189],"iteration":18,"passed_time":0.1488551557,"remaining_time":2.984937595},
{"learn":[40.37509621],"iteration":19,"passed_time":0.1491044843,"remaining_time":2.832985201},
{"learn":[39.45385668],"iteration":20,"passed_time":0.1493578473,"remaining_time":2.69555353},
{"learn":[38.49174617],"iteration":21,"passed_time":0.1496112143,"remaining_time":2.570592683},
{"learn":[37.69050643],"iteration":22,"passed_time":0.1499289304,"remaining_time":2.457530729},
{"learn":[36.80673463],"iteration":23,"passed_time":0.1502127794,"remaining_time":2.353333545},
{"learn":[35.89079414],"iteration":24,"passed_time":0.150451481,"remaining_time":2.256772216},
{"learn":[35.10693717],"iteration":25,"passed_time":0.1507321207,"remaining_time":2.168223582},
{"learn":[34.48725119],"iteration":26,"passed_time":0.1509682729,"remaining_time":2.085598733},
{"learn":[34.06505002],"iteration":27,"passed_time":0.151199418,"remaining_time":2.008792268},
{"learn":[33.36027055],"iteration":28,"passed_time":0.1514479028,"remaining_time":1.937488688},
{"learn":[32.73117894],"iteration":29,"passed_time":0.1517184646,"remaining_time":1.871194397},
{"learn":[31.98666427],"iteration":30,"passed_time":0.1519230139,"remaining_time":1.808373939},
{"learn":[31.4857399],"iteration":31,"passed_time":0.1521507718,"remaining_time":1.749733876},
{"learn":[30.99836729],"iteration":32,"passed_time":0.1523969177,"remaining_time":1.694838449},
{"learn":[30.4386225],"iteration":33,"passed_time":0.1526242441,"remaining_time":1.642955099},
{"learn":[29.91340167],"iteration":34,"passed_time":0.1528631595,"remaining_time":1.594144378},
{"learn":[29.41460179],"iteration":35,"passed_time":0.1531207194,"remaining_time":1.548220607},
{"learn":[28.96929468],"iteration":36,"passed_time":0.1533710126,"remaining_time":1.504693989},
{"learn":[28.47076732],"iteration":37,"passed_time":0.1535951543,"remaining_time":1.463195944},
{"learn":[27.99617644],"iteration":38,"passed_time":0.1538100627,"remaining_time":1.423729042},
{"learn":[27.61585858],"iteration":39,"passed_time":0.1540521307,"remaining_time":1.386469176},
{"learn":[27.26746224],"iteration":40,"passed_time":0.1542455619,"remaining_time":1.350589189},
{"learn":[26.87321425],"iteration":41,"passed_time":0.1544682112,"remaining_time":1.31665761},
{"learn":[26.42727342],"iteration":42,"passed_time":0.1547126101,"remaining_time":1.284474461},
{"learn":[26.11558941],"iteration":43,"passed_time":0.1549064328,"remaining_time":1.253333866},
{"learn":[25.90209634],"iteration":44,"passed_time":0.155184131,"remaining_time":1.224230366},
{"learn":[25.59865858],"iteration":45,"passed_time":0.1554017871,"remaining_time":1.1959181},
{"learn":[25.45588276],"iteration":46,"passed_time":0.1556610391,"remaining_time":1.169113762},
{"learn":[25.04648734],"iteration":47,"passed_time":0.1558800547,"remaining_time":1.143120401},
{"learn":[24.80960526],"iteration":48,"passed_time":0.156099516,"remaining_time":1.118182247},
{"learn":[24.47499918],"iteration":49,"passed_time":0.156307433,"remaining_time":1.094152031},
{"learn":[24.1461265],"iteration":50,"passed_time":0.1565380363,"remaining_time":1.071211268},
{"learn":[23.80679092],"iteration":51,"passed_time":0.1567413563,"remaining_time":1.048961384},
{"learn":[23.58019978],"iteration":52,"passed_time":0.1569893414,"remaining_time":1.027835876},
{"learn":[23.39359239],"iteration":53,"passed_time":0.1574254429,"remaining_time":1.008688949},
{"learn":[23.11648392],"iteration":54,"passed_time":0.1578531371,"remaining_time":0.9901696782},
{"learn":[22.87868915],"iteration":55,"passed_time":0.1582006183,"remaining_time":0.9718037983},
{"learn":[22.71268064],"iteration":56,"passed_time":0.1584545238,"remaining_time":0.953507047},
{"learn":[22.55925556],"iteration":57,"passed_time":0.1587303313,"remaining_time":0.9359616088},
{"learn":[22.29523761],"iteration":58,"passed_time":0.1589657507,"remaining_time":0.9187681524},
{"learn":[21.99183057],"iteration":59,"passed_time":0.1591879323,"remaining_time":0.9020649497},
{"learn":[21.80500437],"iteration":60,"passed_time":0.1594047714,"remaining_time":0.8858724179},
{"learn":[21.66041951],"iteration":61,"passed_time":0.1596667618,"remaining_time":0.8704413791},
{"learn":[21.42254837],"iteration":62,"passed_time":0.1599244272,"remaining_time":0.8554687616},
{"learn":[21.13371862],"iteration":63,"passed_time":0.1601532488,"remaining_time":0.8408045561},
{"learn":[20.84975733],"iteration":64,"passed_time":0.1603788823,"remaining_time":0.8265680856},
{"learn":[20.63783257],"iteration":65,"passed_time":0.1606339436,"remaining_time":0.8129051083},
{"learn":[20.46274126],"iteration":66,"passed_time":0.160932297,"remaining_time":0.7998575359},
{"learn":[20.33114709],"iteration":67,"passed_time":0.1611741512,"remaining_time":0.7869090913},
{"learn":[20.17187551],"iteration":68,"passed_time":0.1615890352,"remaining_time":0.7751589951},
{"learn":[19.93446562],"iteration":69,"passed_time":0.1618223315,"remaining_time":0.7628767056},
{"learn":[19.78811941],"iteration":70,"passed_time":0.1621450437,"remaining_time":0.7513481604},
{"learn":[19.62409273],"iteration":71,"passed_time":0.162364519,"remaining_time":0.7396605865},
{"learn":[19.51100211],"iteration":72,"passed_time":0.162595964,"remaining_time":0.7283408252},
{"learn":[19.28912214],"iteration":73,"passed_time":0.1628238002,"remaining_time":0.7173048494},
{"learn":[19.05267816],"iteration":74,"passed_time":0.1630455602,"remaining_time":0.706530761},
{"learn":[18.94506148],"iteration":75,"passed_time":0.163274633,"remaining_time":0.6960655405},
{"learn":[18.76259821],"iteration":76,"passed_time":0.1635261909,"remaining_time":0.685960515},
{"learn":[18.62538091],"iteration":77,"passed_time":0.1637487499,"remaining_time":0.6759884292},
{"learn":[18.42948735],"iteration":78,"passed_time":0.1639939478,"remaining_time":0.6663551551},
{"learn":[18.32959037],"iteration":79,"passed_time":0.1641977141,"remaining_time":0.6567908565},
{"learn":[18.20268251],"iteration":80,"passed_time":0.1643876447,"remaining_time":0.6474031934},
{"learn":[18.0188577],"iteration":81,"passed_time":0.1646941483,"remaining_time":0.6386919409},
{"learn":[17.95314458],"iteration":82,"passed_time":0.1649315398,"remaining_time":0.6299192544},
{"learn":[17.78790073],"iteration":83,"passed_time":0.165185154,"remaining_time":0.6214108175},
{"learn":[17.58554883],"iteration":84,"passed_time":0.1654715841,"remaining_time":0.6132182235},
{"learn":[17.38801577],"iteration":85,"passed_time":0.1656933448,"remaining_time":0.6049733754},
{"learn":[17.325185],"iteration":86,"passed_time":0.1659369801,"remaining_time":0.5969916642},
{"learn":[17.26562179],"iteration":87,"passed_time":0.1662828129,"remaining_time":0.5895481548},
{"learn":[17.07394162],"iteration":88,"passed_time":0.1665228286,"remaining_time":0.5818943786},
{"learn":[16.96528039],"iteration":89,"passed_time":0.1667274353,"remaining_time":0.5742833883},
{"learn":[16.77388506],"iteration":90,"passed_time":0.1669455036,"remaining_time":0.5668808859},
{"learn":[16.71919913],"iteration":91,"passed_time":0.1672334472,"remaining_time":0.5598684972},
{"learn":[16.63246869],"iteration":92,"passed_time":0.1677204225,"remaining_time":0.5536577389},
{"learn":[16.51583189],"iteration":93,"passed_time":0.1680239769,"remaining_time":0.5469716695},
{"learn":[16.46310871],"iteration":94,"passed_time":0.1682778954,"remaining_time":0.5402606117},
{"learn":[16.3147385],"iteration":95,"passed_time":0.1685105316,"remaining_time":0.5336166835},
{"learn":[16.17000359],"iteration":96,"passed_time":0.1687310785,"remaining_time":0.5270671833},
{"learn":[16.00903788],"iteration":97,"passed_time":0.1689621975,"remaining_time":0.520679425},
{"learn":[15.95853658],"iteration":98,"passed_time":0.1691959046,"remaining_time":0.514423912},
{"learn":[15.87746602],"iteration":99,"passed_time":0.1695054162,"remaining_time":0.5085162485},
{"learn":[15.71428576],"iteration":100,"passed_time":0.1697136772,"remaining_time":0.5024196979},
{"learn":[15.57952903],"iteration":101,"passed_time":0.1699154527,"remaining_time":0.4964196558},
{"learn":[15.48732218],"iteration":102,"passed_time":0.1701333172,"remaining_time":0.4905785943},
{"learn":[15.3251695],"iteration":103,"passed_time":0.1703623545,"remaining_time":0.4848774706},
{"learn":[15.16480685],"iteration":104,"passed_time":0.1705703056,"remaining_time":0.4792213348},
{"learn":[15.06423167],"iteration":105,"passed_time":0.1708084283,"remaining_time":0.4737516786},
{"learn":[14.97507288],"iteration":106,"passed_time":0.1710353753,"remaining_time":0.4683492052},
{"learn":[14.93111066],"iteration":107,"passed_time":0.1712386886,"remaining_time":0.4629786766},
{"learn":[14.78385903],"iteration":108,"passed_time":0.1714358838,"remaining_time":0.4576866255},
{"learn":[14.6351817],"iteration":109,"passed_time":0.1716206629,"remaining_time":0.4524544748},
{"learn":[14.51494995],"iteration":110,"passed_time":0.1718105614,"remaining_time":0.4473265968},
{"learn":[14.47176582],"iteration":111,"passed_time":0.1720833175,"remaining_time":0.4424999592},
{"learn":[14.40341991],"iteration":112,"passed_time":0.1723115778,"remaining_time":0.43764091},
{"learn":[14.26849757],"iteration":113,"passed_time":0.1725383885,"remaining_time":0.4328594658},
{"learn":[14.1334418],"iteration":114,"passed_time":0.1728063962,"remaining_time":0.4282593298},
{"learn":[14.03059523],"iteration":115,"passed_time":0.1734583865,"remaining_time":0.4246739808},
{"learn":[13.95316128],"iteration":116,"passed_time":0.1738185577,"remaining_time":0.4204329216},
{"learn":[13.82168924],"iteration":117,"passed_time":0.1741164979,"remaining_time":0.4161089188},
{"learn":[13.7575787],"iteration":118,"passed_time":0.1743670097,"remaining_time":0.4117405859},
{"learn":[13.71800627],"iteration":119,"passed_time":0.1745896148,"remaining_time":0.4073757679},
{"learn":[13.68044983],"iteration":120,"passed_time":0.1748290333,"remaining_time":0.4031181842},
{"learn":[13.57571095],"iteration":121,"passed_time":0.1750376497,"remaining_time":0.3988562838},
{"learn":[13.44794683],"iteration":122,"passed_time":0.1753237147,"remaining_time":0.3948347072},
{"learn":[13.33730975],"iteration":123,"passed_time":0.1755951203,"remaining_time":0.3908407517},
{"learn":[13.21658597],"iteration":124,"passed_time":0.1758264959,"remaining_time":0.3868182909},
{"learn":[13.17905737],"iteration":125,"passed_time":0.1760992823,"remaining_time":0.3829460584},
{"learn":[13.07974217],"iteration":126,"passed_time":0.1763342775,"remaining_time":0.3790492737},
{"learn":[13.02100408],"iteration":127,"passed_time":0.1766425648,"remaining_time":0.3753654502},
{"learn":[12.9427998],"iteration":128,"passed_time":0.1769475739,"remaining_time":0.3717270738},
{"learn":[12.90828681],"iteration":129,"passed_time":0.1771820059,"remaining_time":0.3679933968},
{"learn":[12.81467812],"iteration":130,"passed_time":0.1774156612,"remaining_time":0.3643115486},
{"learn":[12.75006288],"iteration":131,"passed_time":0.1777241596,"remaining_time":0.3608338999},
{"learn":[12.63540556],"iteration":132,"passed_time":0.177981185,"remaining_time":0.3573005744},
{"learn":[12.53551528],"iteration":133,"passed_time":0.1782542431,"remaining_time":0.353847975},
{"learn":[12.41909226],"iteration":134,"passed_time":0.178555518,"remaining_time":0.3504978686},
{"learn":[12.38710139],"iteration":135,"passed_time":0.1788021936,"remaining_time":0.3470866112},
{"learn":[12.28258197],"iteration":136,"passed_time":0.1790438989,"remaining_time":0.3437120103},
{"learn":[12.22979611],"iteration":137,"passed_time":0.1793147156,"remaining_time":0.3404380832},
{"learn":[12.19776307],"iteration":138,"passed_time":0.1796874371,"remaining_time":0.3373987128},
{"learn":[12.11830442],"iteration":139,"passed_time":0.179996318,"remaining_time":0.3342788762},
{"learn":[12.02278839],"iteration":140,"passed_time":0.1803238156,"remaining_time":0.3312331081},
{"learn":[11.9534435],"iteration":141,"passed_time":0.1806839033,"remaining_time":0.3282848383},
{"learn":[11.88437804],"iteration":142,"passed_time":0.1810717405,"remaining_time":0.3254226385},
{"learn":[11.79510367],"iteration":143,"passed_time":0.1814158032,"remaining_time":0.3225169835},
{"learn":[11.69525979],"iteration":144,"passed_time":0.1817788892,"remaining_time":0.3196801155},
{"learn":[11.59210509],"iteration":145,"passed_time":0.1822834437,"remaining_time":0.3171232514},
{"learn":[11.51602675],"iteration":146,"passed_time":0.1825522973,"remaining_time":0.3141886477},
{"learn":[11.48549372],"iteration":147,"passed_time":0.1828410379,"remaining_time":0.3113239293},
{"learn":[11.4565039],"iteration":148,"passed_time":0.1831120226,"remaining_time":0.3084638769},
{"learn":[11.38453426],"iteration":149,"passed_time":0.1833560373,"remaining_time":0.3055933955},
{"learn":[11.32301425],"iteration":150,"passed_time":0.1835723626,"remaining_time":0.3027120417},
{"learn":[11.23922791],"iteration":151,"passed_time":0.1837975626,"remaining_time":0.2998802337},
{"learn":[11.21254028],"iteration":152,"passed_time":0.1840108468,"remaining_time":0.2970632625},
{"learn":[11.12214322],"iteration":153,"passed_time":0.1842070312,"remaining_time":0.2942527901},
{"learn":[11.05905536],"iteration":154,"passed_time":0.184449932,"remaining_time":0.2915498924},
{"learn":[10.9677654],"iteration":155,"passed_time":0.1847246805,"remaining_time":0.2889283465},
{"learn":[10.8918039],"iteration":156,"passed_time":0.1849535241,"remaining_time":0.2862656456},
{"learn":[10.86517576],"iteration":157,"passed_time":0.1852210038,"remaining_time":0.2836929298},
{"learn":[10.80008164],"iteration":158,"passed_time":0.1854320447,"remaining_time":0.2810636652},
{"learn":[10.72931964],"iteration":159,"passed_time":0.1856334427,"remaining_time":0.278450164},
{"learn":[10.64219927],"iteration":160,"passed_time":0.1858610326,"remaining_time":0.275905508},
{"learn":[10.61371928],"iteration":161,"passed_time":0.1861350563,"remaining_time":0.2734576754},
{"learn":[10.58832732],"iteration":162,"passed_time":0.1865201739,"remaining_time":0.2711980442},
{"learn":[10.52543492],"iteration":163,"passed_time":0.1867512876,"remaining_time":0.2687396577},
{"learn":[10.45139826],"iteration":164,"passed_time":0.1869584971,"remaining_time":0.2662742231},
{"learn":[10.36627109],"iteration":165,"passed_time":0.1871612746,"remaining_time":0.2638297486},
{"learn":[10.29200921],"iteration":166,"passed_time":0.1873598567,"remaining_time":0.2614062671},
{"learn":[10.26768124],"iteration":167,"passed_time":0.1875633618,"remaining_time":0.259016071},
{"learn":[10.24155478],"iteration":168,"passed_time":0.188083199,"remaining_time":0.257084136},
{"learn":[10.16186234],"iteration":169,"passed_time":0.188376255,"remaining_time":0.2548619921},
{"learn":[10.10895636],"iteration":170,"passed_time":0.188614795,"remaining_time":0.2525894038},
{"learn":[10.08351488],"iteration":171,"passed_time":0.1888430827,"remaining_time":0.2503268771},
{"learn":[10.01469414],"iteration":172,"passed_time":0.1890747021,"remaining_time":0.2480922392},
{"learn":[9.991627278],"iteration":173,"passed_time":0.1893012663,"remaining_time":0.2458740585},
{"learn":[9.934266933],"iteration":174,"passed_time":0.1896299003,"remaining_time":0.2438098718},
{"learn":[9.858297549],"iteration":175,"passed_time":0.1898918881,"remaining_time":0.2416805848},
{"learn":[9.834127984],"iteration":176,"passed_time":0.1901146329,"remaining_time":0.2395229555},
{"learn":[9.762614245],"iteration":177,"passed_time":0.1903303015,"remaining_time":0.2373782411},
{"learn":[9.739784413],"iteration":178,"passed_time":0.1905482722,"remaining_time":0.2352579227},
{"learn":[9.691807526],"iteration":179,"passed_time":0.1907423261,"remaining_time":0.2331295097},
{"learn":[9.627753446],"iteration":180,"passed_time":0.1910579816,"remaining_time":0.231169602},
{"learn":[9.605722281],"iteration":181,"passed_time":0.1912890812,"remaining_time":0.2291264819},
{"learn":[9.559798364],"iteration":182,"passed_time":0.1915210193,"remaining_time":0.2271041595},
{"learn":[9.501570826],"iteration":183,"passed_time":0.1917358662,"remaining_time":0.2250812342},
{"learn":[9.43160533],"iteration":184,"passed_time":0.1919422005,"remaining_time":0.2230679627},
{"learn":[9.411029779],"iteration":185,"passed_time":0.1921798863,"remaining_time":0.2211101918},
{"learn":[9.389223554],"iteration":186,"passed_time":0.1923901402,"remaining_time":0.2191395715},
{"learn":[9.322396796],"iteration":187,"passed_time":0.192612559,"remaining_time":0.2172013963},
{"learn":[9.270121289],"iteration":188,"passed_time":0.1928246574,"remaining_time":0.2152698556},
{"learn":[9.219891249],"iteration":189,"passed_time":0.1930913725,"remaining_time":0.2134167801},
{"learn":[9.200298878],"iteration":190,"passed_time":0.1933427099,"remaining_time":0.2115634889},
{"learn":[9.14091898],"iteration":191,"passed_time":0.1935627704,"remaining_time":0.2096930013},
{"learn":[9.098933228],"iteration":192,"passed_time":0.1937826652,"remaining_time":0.2078394389},
{"learn":[9.034400358],"iteration":193,"passed_time":0.1939942185,"remaining_time":0.2059938609},
{"learn":[8.976880588],"iteration":194,"passed_time":0.1942339556,"remaining_time":0.2041946713},
{"learn":[8.913711446],"iteration":195,"passed_time":0.1944602332,"remaining_time":0.2023973855},
{"learn":[8.895653137],"iteration":196,"passed_time":0.1946673826,"remaining_time":0.2005963384},
{"learn":[8.875935136],"iteration":197,"passed_time":0.1949553108,"remaining_time":0.1988938019},
{"learn":[8.816850199],"iteration":198,"passed_time":0.1952198005,"remaining_time":0.1971818086},
{"learn":[8.764439599],"iteration":199,"passed_time":0.1954730112,"remaining_time":0.1954730112},
{"learn":[8.724793268],"iteration":200,"passed_time":0.1956710295,"remaining_time":0.193724054},
{"learn":[8.685026281],"iteration":201,"passed_time":0.1958666032,"remaining_time":0.1919880566},
{"learn":[8.640994119],"iteration":202,"passed_time":0.1961153132,"remaining_time":0.1903188014},
{"learn":[8.623729196],"iteration":203,"passed_time":0.1963927724,"remaining_time":0.1886910951},
{"learn":[8.581888111],"iteration":204,"passed_time":0.196628888,"remaining_time":0.1870372349},
{"learn":[8.565386205],"iteration":205,"passed_time":0.1969584108,"remaining_time":0.1854851053},
{"learn":[8.546997474],"iteration":206,"passed_time":0.1972040269,"remaining_time":0.1838665565},
{"learn":[8.494455068],"iteration":207,"passed_time":0.1974557495,"remaining_time":0.1822668457},
{"learn":[8.478015472],"iteration":208,"passed_time":0.1977275797,"remaining_time":0.1806984101},
{"learn":[8.441654695],"iteration":209,"passed_time":0.1980047674,"remaining_time":0.1791471705},
{"learn":[8.387783707],"iteration":210,"passed_time":0.1982837091,"remaining_time":0.1776095783},
{"learn":[8.338786786],"iteration":211,"passed_time":0.1986797462,"remaining_time":0.1761876995},
{"learn":[8.290519473],"iteration":212,"passed_time":0.1989682527,"remaining_time":0.1746810481},
{"learn":[8.255849417],"iteration":213,"passed_time":0.1991904523,"remaining_time":0.1731281501},
{"learn":[8.215613553],"iteration":214,"passed_time":0.1994236951,"remaining_time":0.171597133},
{"learn":[8.200737829],"iteration":215,"passed_time":0.1997879125,"remaining_time":0.1701897032},
{"learn":[8.150226395],"iteration":216,"passed_time":0.2001506624,"remaining_time":0.1687906508},
{"learn":[8.133912696],"iteration":217,"passed_time":0.20038396,"remaining_time":0.1672930308},
{"learn":[8.091762073],"iteration":218,"passed_time":0.2005964172,"remaining_time":0.1657897329},
{"learn":[8.043604691],"iteration":219,"passed_time":0.2008313075,"remaining_time":0.1643165243},
{"learn":[8.029306144],"iteration":220,"passed_time":0.2011055296,"remaining_time":0.1628863792},
{"learn":[8.013839719],"iteration":221,"passed_time":0.2013184511,"remaining_time":0.1614174968},
{"learn":[7.98329116],"iteration":222,"passed_time":0.2016199401,"remaining_time":0.1600301767},
{"learn":[7.969595981],"iteration":223,"passed_time":0.201833497,"remaining_time":0.1585834619},
{"learn":[7.923676527],"iteration":224,"passed_time":0.2020305144,"remaining_time":0.1571348446},
{"learn":[7.887774081],"iteration":225,"passed_time":0.2022310212,"remaining_time":0.1556999898},
{"learn":[7.840990503],"iteration":226,"passed_time":0.2024472677,"remaining_time":0.1542880058},
{"learn":[7.800334997],"iteration":227,"passed_time":0.2026476262,"remaining_time":0.152874525},
{"learn":[7.770890143],"iteration":228,"passed_time":0.2028553675,"remaining_time":0.1514771521},
{"learn":[7.728860679],"iteration":229,"passed_time":0.2030612428,"remaining_time":0.1500887447},
{"learn":[7.69997949],"iteration":230,"passed_time":0.2032617824,"remaining_time":0.1487066719},
{"learn":[7.68690457],"iteration":231,"passed_time":0.2034552163,"remaining_time":0.1473296394},
{"learn":[7.649269851],"iteration":232,"passed_time":0.2036696516,"remaining_time":0.145977819},
{"learn":[7.606757811],"iteration":233,"passed_time":0.2038720992,"remaining_time":0.1446272157},
{"learn":[7.572792264],"iteration":234,"passed_time":0.2040758361,"remaining_time":0.1432872892},
{"learn":[7.560392163],"iteration":235,"passed_time":0.2043301164,"remaining_time":0.1419921148},
{"learn":[7.520702672],"iteration":236,"passed_time":0.2045736922,"remaining_time":0.1406983621},
{"learn":[7.508744728],"iteration":237,"passed_time":0.2048777737,"remaining_time":0.1394546191},
{"learn":[7.468400506],"iteration":238,"passed_time":0.2052211516,"remaining_time":0.1382452109},
{"learn":[7.441968763],"iteration":239,"passed_time":0.2055627001,"remaining_time":0.1370418},
{"learn":[7.428395524],"iteration":240,"passed_time":0.2058111528,"remaining_time":0.1357841215},
{"learn":[7.416625345],"iteration":241,"passed_time":0.2061705804,"remaining_time":0.1346072385},
{"learn":[7.379905138],"iteration":242,"passed_time":0.2064697145,"remaining_time":0.1333981283},
{"learn":[7.367521173],"iteration":243,"passed_time":0.2066980584,"remaining_time":0.1321512176},
{"learn":[7.335284503],"iteration":244,"passed_time":0.2069012321,"remaining_time":0.1308966979},
{"learn":[7.307158738],"iteration":245,"passed_time":0.2071309108,"remaining_time":0.1296673181},
{"learn":[7.295865737],"iteration":246,"passed_time":0.2073422075,"remaining_time":0.1284346468},
{"learn":[7.284595441],"iteration":247,"passed_time":0.2075322644,"remaining_time":0.1271971943},
{"learn":[7.261111355],"iteration":248,"passed_time":0.2077543872,"remaining_time":0.1259876003},
{"learn":[7.22453016],"iteration":249,"passed_time":0.2079627798,"remaining_time":0.1247776679},
{"learn":[7.188236254],"iteration":250,"passed_time":0.2081805348,"remaining_time":0.1235812737},
{"learn":[7.156601185],"iteration":251,"passed_time":0.2084024839,"remaining_time":0.1223951096},
{"learn":[7.146021249],"iteration":252,"passed_time":0.2086118513,"remaining_time":0.1212092575},
{"learn":[7.135655624],"iteration":253,"passed_time":0.2088517969,"remaining_time":0.1200486706},
{"learn":[7.107475714],"iteration":254,"passed_time":0.2091733239,"remaining_time":0.118941694},
{"learn":[7.097554138],"iteration":255,"passed_time":0.2094061038,"remaining_time":0.1177909334},
{"learn":[7.085967619],"iteration":256,"passed_time":0.209698607,"remaining_time":0.1166805478},
{"learn":[7.053595993],"iteration":257,"passed_time":0.2099370881,"remaining_time":0.1155467694},
{"learn":[7.043814785],"iteration":258,"passed_time":0.2101631004,"remaining_time":0.1144131164},
{"learn":[7.034195109],"iteration":259,"passed_time":0.2103975738,"remaining_time":0.1132910013},
{"learn":[7.012410145],"iteration":260,"passed_time":0.2107138853,"remaining_time":0.1122192722},
{"learn":[6.980635907],"iteration":261,"passed_time":0.2110326028,"remaining_time":0.1111545771},
{"learn":[6.951843248],"iteration":262,"passed_time":0.2113319924,"remaining_time":0.1100854866},
{"learn":[6.922924476],"iteration":263,"passed_time":0.2115869081,"remaining_time":0.1089993163},
{"learn":[6.891314806],"iteration":264,"passed_time":0.2118726831,"remaining_time":0.1079351405},
{"learn":[6.88201909],"iteration":265,"passed_time":0.2121119012,"remaining_time":0.1068533637},
{"learn":[6.872871049],"iteration":266,"passed_time":0.2123500483,"remaining_time":0.1057773649},
{"learn":[6.842220898],"iteration":267,"passed_time":0.212558616,"remaining_time":0.1046930497},
{"learn":[6.818360007],"iteration":268,"passed_time":0.2128341676,"remaining_time":0.103647866},
{"learn":[6.80964837],"iteration":269,"passed_time":0.2130695054,"remaining_time":0.1025890211},
{"learn":[6.801068435],"iteration":270,"passed_time":0.2132639969,"remaining_time":0.1015168104},
{"learn":[6.791120451],"iteration":271,"passed_time":0.2135868278,"remaining_time":0.1005114484},
{"learn":[6.772443891],"iteration":272,"passed_time":0.2138587003,"remaining_time":0.09948738073},
{"learn":[6.743098315],"iteration":273,"passed_time":0.2141040525,"remaining_time":0.0984566081},
{"learn":[6.717157798],"iteration":274,"passed_time":0.2143472295,"remaining_time":0.09743055888},
{"learn":[6.690114686],"iteration":275,"passed_time":0.2145844487,"remaining_time":0.09640750594},
{"learn":[6.680935505],"iteration":276,"passed_time":0.2148539937,"remaining_time":0.09540448095},
{"learn":[6.65377076],"iteration":277,"passed_time":0.2150599065,"remaining_time":0.09437880788},
{"learn":[6.635425649],"iteration":278,"passed_time":0.2152530184,"remaining_time":0.0933534596},
{"learn":[6.608045684],"iteration":279,"passed_time":0.2155219511,"remaining_time":0.09236655048},
{"learn":[6.581000942],"iteration":280,"passed_time":0.215735828,"remaining_time":0.09136143605},
{"learn":[6.565078816],"iteration":281,"passed_time":0.2160329241,"remaining_time":0.09039675548},
{"learn":[6.557008973],"iteration":282,"passed_time":0.2162967645,"remaining_time":0.08942304397},
{"learn":[6.539580034],"iteration":283,"passed_time":0.2165407539,"remaining_time":0.0884462234},
{"learn":[6.531663841],"iteration":284,"passed_time":0.2167790346,"remaining_time":0.08747224202},
{"learn":[6.523992082],"iteration":285,"passed_time":0.2169953271,"remaining_time":0.08649464089},
{"learn":[6.516498457],"iteration":286,"passed_time":0.2174370652,"remaining_time":0.08561110929},
{"learn":[6.497655847],"iteration":287,"passed_time":0.2176644651,"remaining_time":0.08464729197},
{"learn":[6.472572588],"iteration":288,"passed_time":0.217887421,"remaining_time":0.0836868641},
{"learn":[6.450313746],"iteration":289,"passed_time":0.2181768744,"remaining_time":0.08275674546},
{"learn":[6.442064207],"iteration":290,"passed_time":0.2184030096,"remaining_time":0.08180731289},
{"learn":[6.434727583],"iteration":291,"passed_time":0.2186075115,"remaining_time":0.08085483301},
{"learn":[6.411831423],"iteration":292,"passed_time":0.218803756,"remaining_time":0.07990444331},
{"learn":[6.397406175],"iteration":293,"passed_time":0.2189979355,"remaining_time":0.07895843932},
{"learn":[6.381728725],"iteration":294,"passed_time":0.2192079789,"remaining_time":0.07802317894},
{"learn":[6.357922571],"iteration":295,"passed_time":0.2194870065,"remaining_time":0.07711705634},
{"learn":[6.33748946],"iteration":296,"passed_time":0.2197543412,"remaining_time":0.07621110149},
{"learn":[6.31406731],"iteration":297,"passed_time":0.2200138298,"remaining_time":0.0753067471},
{"learn":[6.300580344],"iteration":298,"passed_time":0.2202382053,"remaining_time":0.07439484527},
{"learn":[6.277348408],"iteration":299,"passed_time":0.2204422341,"remaining_time":0.07348074471},
{"learn":[6.270395399],"iteration":300,"passed_time":0.2206824763,"remaining_time":0.07258327294},
{"learn":[6.255814167],"iteration":301,"passed_time":0.2208874812,"remaining_time":0.07167871906},
{"learn":[6.248941735],"iteration":302,"passed_time":0.2211143393,"remaining_time":0.07078577858},
{"learn":[6.232434541],"iteration":303,"passed_time":0.2213343089,"remaining_time":0.06989504492},
{"learn":[6.214493005],"iteration":304,"passed_time":0.2215500183,"remaining_time":0.06900738274},
{"learn":[6.207983083],"iteration":305,"passed_time":0.2217889904,"remaining_time":0.0681312585},
{"learn":[6.195261204],"iteration":306,"passed_time":0.2219863372,"remaining_time":0.06724667545},
{"learn":[6.176390145],"iteration":307,"passed_time":0.2221888369,"remaining_time":0.06636809413},
{"learn":[6.155939857],"iteration":308,"passed_time":0.2224024064,"remaining_time":0.06549714881},
{"learn":[6.142043441],"iteration":309,"passed_time":0.2226042934,"remaining_time":0.06462705293},
{"learn":[6.123061737],"iteration":310,"passed_time":0.2228009294,"remaining_time":0.0637597515},
{"learn":[6.116924594],"iteration":311,"passed_time":0.2230118207,"remaining_time":0.06290076993},
{"learn":[6.096497427],"iteration":312,"passed_time":0.22322657,"remaining_time":0.06204700188},
{"learn":[6.090627495],"iteration":313,"passed_time":0.2234279099,"remaining_time":0.06119363136},
{"learn":[6.078959072],"iteration":314,"passed_time":0.2236301042,"remaining_time":0.06034463129},
{"learn":[6.072675711],"iteration":315,"passed_time":0.2238467755,"remaining_time":0.05950357325},
{"learn":[6.053940486],"iteration":316,"passed_time":0.2241281176,"remaining_time":0.05868338727},
{"learn":[6.034452374],"iteration":317,"passed_time":0.2243907735,"remaining_time":0.05786177179},
{"learn":[6.021580653],"iteration":318,"passed_time":0.2246132431,"remaining_time":0.0570334567},
{"learn":[6.015798099],"iteration":319,"passed_time":0.2248208187,"remaining_time":0.05620520467},
{"learn":[5.999619069],"iteration":320,"passed_time":0.2250351571,"remaining_time":0.05538248416},
{"learn":[5.982429317],"iteration":321,"passed_time":0.2252401273,"remaining_time":0.05456127307},
{"learn":[5.97166223],"iteration":322,"passed_time":0.2254428855,"remaining_time":0.05374335041},
{"learn":[5.956617082],"iteration":323,"passed_time":0.2256678937,"remaining_time":0.05293444419},
{"learn":[5.938381402],"iteration":324,"passed_time":0.2258821232,"remaining_time":0.05212664383},
{"learn":[5.928086126],"iteration":325,"passed_time":0.2261053537,"remaining_time":0.05132452814},
{"learn":[5.922719423],"iteration":326,"passed_time":0.2263349562,"remaining_time":0.05052737555},
{"learn":[5.917386531],"iteration":327,"passed_time":0.2265670954,"remaining_time":0.04973424045},
{"learn":[5.912304348],"iteration":328,"passed_time":0.2267957172,"remaining_time":0.04894375659},
{"learn":[5.907249581],"iteration":329,"passed_time":0.2269956267,"remaining_time":0.04815058748},
{"learn":[5.890588342],"iteration":330,"passed_time":0.2272044763,"remaining_time":0.04736286667},
{"learn":[5.873224405],"iteration":331,"passed_time":0.2274009807,"remaining_time":0.04657610448},
{"learn":[5.858168235],"iteration":332,"passed_time":0.2276238925,"remaining_time":0.0457982006},
{"learn":[5.853134144],"iteration":333,"passed_time":0.2278502151,"remaining_time":0.04502429401},
{"learn":[5.847636684],"iteration":334,"passed_time":0.2280617036,"remaining_time":0.04425077832},
{"learn":[5.837109595],"iteration":335,"passed_time":0.2282820053,"remaining_time":0.04348228672},
{"learn":[5.82748284],"iteration":336,"passed_time":0.2285342373,"remaining_time":0.04272301765},
{"learn":[5.812731713],"iteration":337,"passed_time":0.2287554936,"remaining_time":0.04196106688},
{"learn":[5.79659961],"iteration":338,"passed_time":0.2289722826,"remaining_time":0.04120150217},
{"learn":[5.782480969],"iteration":339,"passed_time":0.2292593366,"remaining_time":0.04045753},
{"learn":[5.769508323],"iteration":340,"passed_time":0.2294745229,"remaining_time":0.03970380308},
{"learn":[5.764741756],"iteration":341,"passed_time":0.2296874451,"remaining_time":0.03895284156},
{"learn":[5.751432131],"iteration":342,"passed_time":0.2298876258,"remaining_time":0.03820289992},
{"learn":[5.742566371],"iteration":343,"passed_time":0.2301066608,"remaining_time":0.03745922386},
{"learn":[5.733969998],"iteration":344,"passed_time":0.2303817511,"remaining_time":0.03672752554},
{"learn":[5.729434065],"iteration":345,"passed_time":0.2307295096,"remaining_time":0.03600980786},
{"learn":[5.725025572],"iteration":346,"passed_time":0.2310023846,"remaining_time":0.03528278497},
{"learn":[5.720731434],"iteration":347,"passed_time":0.2312525155,"remaining_time":0.03455497358},
{"learn":[5.715962926],"iteration":348,"passed_time":0.2314973974,"remaining_time":0.03382913257},
{"learn":[5.706710901],"iteration":349,"passed_time":0.2318237844,"remaining_time":0.03311768348},
{"learn":[5.693784227],"iteration":350,"passed_time":0.2320578643,"remaining_time":0.03239554231},
{"learn":[5.680082875],"iteration":351,"passed_time":0.2323489485,"remaining_time":0.03168394752},
{"learn":[5.665943949],"iteration":352,"passed_time":0.2326018506,"remaining_time":0.03096965149},
{"learn":[5.651262869],"iteration":353,"passed_time":0.2328982192,"remaining_time":0.0302636104},
{"learn":[5.637953644],"iteration":354,"passed_time":0.2331119163,"remaining_time":0.02954939784},
{"learn":[5.633757119],"iteration":355,"passed_time":0.2333156084,"remaining_time":0.02883676059},
{"learn":[5.626065703],"iteration":356,"passed_time":0.2335196974,"remaining_time":0.02812702238},
{"learn":[5.622087418],"iteration":357,"passed_time":0.2337196664,"remaining_time":0.02741962567},
{"learn":[5.618143103],"iteration":358,"passed_time":0.2339271044,"remaining_time":0.02671590886},
{"learn":[5.610334392],"iteration":359,"passed_time":0.2341481556,"remaining_time":0.02601646174},
{"learn":[5.601683529],"iteration":360,"passed_time":0.2343692957,"remaining_time":0.0253196746},
{"learn":[5.588838728],"iteration":361,"passed_time":0.2345597681,"remaining_time":0.0246222961},
{"learn":[5.584625224],"iteration":362,"passed_time":0.2347838383,"remaining_time":0.02393113504},
{"learn":[5.573552568],"iteration":363,"passed_time":0.235027964,"remaining_time":0.02324452391},
{"learn":[5.563448439],"iteration":364,"passed_time":0.2352577789,"remaining_time":0.0225589651},
{"learn":[5.559730445],"iteration":365,"passed_time":0.2354636396,"remaining_time":0.02187367144},
{"learn":[5.548917484],"iteration":366,"passed_time":0.2357221007,"remaining_time":0.02119572023},
{"learn":[5.541600005],"iteration":367,"passed_time":0.2359116425,"remaining_time":0.02051405587},
{"learn":[5.53038133],"iteration":368,"passed_time":0.2363124513,"remaining_time":0.01985280756},
{"learn":[5.518351292],"iteration":369,"passed_time":0.236605555,"remaining_time":0.01918423419},
{"learn":[5.506043102],"iteration":370,"passed_time":0.2368616204,"remaining_time":0.01851478974},
{"learn":[5.494468011],"iteration":371,"passed_time":0.2371827647,"remaining_time":0.01785246616},
{"learn":[5.488923308],"iteration":372,"passed_time":0.2375473314,"remaining_time":0.01719511514},
{"learn":[5.485461892],"iteration":373,"passed_time":0.2378086338,"remaining_time":0.01653215101},
{"learn":[5.47430157],"iteration":374,"passed_time":0.2380376918,"remaining_time":0.01586917946},
{"learn":[5.465315449],"iteration":375,"passed_time":0.2382705986,"remaining_time":0.01520876161},
{"learn":[5.458834626],"iteration":376,"passed_time":0.2384827452,"remaining_time":0.0145493452},
{"learn":[5.452242195],"iteration":377,"passed_time":0.2387301504,"remaining_time":0.01389434738},
{"learn":[5.443151036],"iteration":378,"passed_time":0.2389725003,"remaining_time":0.01324122033},
{"learn":[5.432228899],"iteration":379,"passed_time":0.2392109621,"remaining_time":0.01259005063},
{"learn":[5.424164095],"iteration":380,"passed_time":0.2394440602,"remaining_time":0.01194077991},
{"learn":[5.420985065],"iteration":381,"passed_time":0.2396720246,"remaining_time":0.01129344619},
{"learn":[5.417819719],"iteration":382,"passed_time":0.2399043442,"remaining_time":0.01064849569},
{"learn":[5.408499959],"iteration":383,"passed_time":0.2401821515,"remaining_time":0.01000758965},
{"learn":[5.401592586],"iteration":384,"passed_time":0.2404611083,"remaining_time":0.009368614608},
{"learn":[5.398211966],"iteration":385,"passed_time":0.2406792193,"remaining_time":0.00872929811},
{"learn":[5.395198407],"iteration":386,"passed_time":0.2409966922,"remaining_time":0.008095496122},
{"learn":[5.3922051],"iteration":387,"passed_time":0.2412249693,"remaining_time":0.007460566061},
{"learn":[5.382527426],"iteration":388,"passed_time":0.2414562884,"remaining_time":0.006827812783},
{"learn":[5.372503385],"iteration":389,"passed_time":0.2417121153,"remaining_time":0.006197746546},
{"learn":[5.364668295],"iteration":390,"passed_time":0.2419332507,"remaining_time":0.005568796052},
{"learn":[5.355376098],"iteration":391,"passed_time":0.2421721828,"remaining_time":0.004942289444},
{"learn":[5.349446546],"iteration":392,"passed_time":0.2424312668,"remaining_time":0.004318114167},
{"learn":[5.343782718],"iteration":393,"passed_time":0.242664531,"remaining_time":0.00369539895},
{"learn":[5.334221919],"iteration":394,"passed_time":0.2429090281,"remaining_time":0.003074797824},
{"learn":[5.324013427],"iteration":395,"passed_time":0.2431477217,"remaining_time":0.002456037593},
{"learn":[5.318572467],"iteration":396,"passed_time":0.243387054,"remaining_time":0.001839196881},
{"learn":[5.310930457],"iteration":397,"passed_time":0.2435948841,"remaining_time":0.001224094895},
{"learn":[5.301842696],"iteration":398,"passed_time":0.2439041351,"remaining_time":0.0006112885592},
{"learn":[5.293060794],"iteration":399,"passed_time":0.2442097842,"remaining_time":0}
]}